envparse/__init__.py
envparse/_namespace.py
envparse/_parser.py
envparse/_types.py
python_envparse-0.0.4.dist-info/LICENSE.txt
python_envparse-0.0.4.dist-info/METADATA
python_envparse-0.0.4.dist-info/WHEEL
python_envparse-0.0.4.dist-info/RECORD
